kuhl_haus/bedrock/app/__init__.py
kuhl_haus/bedrock/app/api_keys/__init__.py
kuhl_haus/bedrock/app/api_keys/api_key_auth.py
kuhl_haus/bedrock/app/api_keys/aws_secret_auth.py
kuhl_haus/bedrock/app/api_keys/default_key_auth.py
kuhl_haus/bedrock/app/auth.py
kuhl_haus/bedrock/app/auth2.py
kuhl_haus/bedrock/app/base.py
kuhl_haus/bedrock/app/bedrock.py
kuhl_haus/bedrock/app/env.py
kuhl_haus/bedrock/app/factories/__init__.py
kuhl_haus/bedrock/app/factories/api_keys.py
kuhl_haus/bedrock/app/factories/aws_client_factory.py
kuhl_haus/bedrock/app/helpers/__init__.py
kuhl_haus/bedrock/app/helpers/parameter_store_helper.py
kuhl_haus/bedrock/app/helpers/secrets_manager_helper.py
kuhl_haus/bedrock/app/py.typed
kuhl_haus/bedrock/app/schema.py
kuhl_haus_bedrock_app-0.2.12.dist-info/METADATA
kuhl_haus_bedrock_app-0.2.12.dist-info/WHEEL
kuhl_haus_bedrock_app-0.2.12.dist-info/entry_points.txt
kuhl_haus_bedrock_app-0.2.12.dist-info/licenses/LICENSE.txt
kuhl_haus_bedrock_app-0.2.12.dist-info/RECORD
