Metadata-Version: 2.1
Name: kuhl-haus-bedrock-app
Version: 0.2.12
Summary: Application layer abstraction for integrating with AWS bedrock APIs
Author-Email: Tom Pounders <git@oldschool.engineer>
License: The MIT License (MIT)
Classifier: Development Status :: 4 - Beta
Classifier: Programming Language :: Python
Project-URL: Homepage, https://github.com/kuhl-haus
Project-URL: Documentation, https://github.com/kuhl-haus/kuhl-haus-bedrock-app/wiki
Project-URL: Source, https://github.com/kuhl-haus/kuhl-haus-bedrock-app.git
Project-URL: Changelog, https://github.com/kuhl-haus/kuhl-haus-bedrock-app/commits
Project-URL: Tracker, https://github.com/kuhl-haus/kuhl-haus-bedrock-app/issues
Requires-Python: >=3.12
Requires-Dist: kuhl-haus-metrics
Requires-Dist: attrs
Requires-Dist: boto3
Requires-Dist: botocore
Requires-Dist: colorama
Requires-Dist: dataclasses
Requires-Dist: dataclasses-json
Requires-Dist: dnspython
Requires-Dist: exceptiongroup
Requires-Dist: fastapi
Requires-Dist: iniconfig
Requires-Dist: jmespath
Requires-Dist: marshmallow
Requires-Dist: marshmallow-enum
Requires-Dist: mypy-extensions
Requires-Dist: packaging
Requires-Dist: pluggy
Requires-Dist: python-dateutil
Requires-Dist: s3transfer
Requires-Dist: six
Requires-Dist: tomli
Requires-Dist: typing-inspect
Requires-Dist: typing-extensions
Requires-Dist: urllib3
Requires-Dist: importlib-metadata
Requires-Dist: pydantic
Requires-Dist: numpy
Requires-Dist: requests
Requires-Dist: tiktoken
Provides-Extra: testing
Requires-Dist: setuptools; extra == "testing"
Requires-Dist: pdm-backend; extra == "testing"
Requires-Dist: pytest; extra == "testing"
Requires-Dist: pytest-cov; extra == "testing"
Requires-Dist: pytest-asyncio; extra == "testing"
Requires-Dist: httpx; extra == "testing"
Requires-Dist: starlette; extra == "testing"
